coords_nsga2/__init__.py
coords_nsga2/algorithm.py
coords_nsga2/spatial.py
coords_nsga2/utils.py
coords_nsga2/operators/__init__.py
coords_nsga2/operators/crossover.py
coords_nsga2/operators/mutation.py
coords_nsga2/operators/selection.py
coords_nsga2/visualization/__init__.py
coords_nsga2/visualization/constraint_violations.py
coords_nsga2/visualization/objective_correlations.py
coords_nsga2/visualization/objective_distributions.py
coords_nsga2/visualization/optimal_coords.py
coords_nsga2/visualization/parallel_coordinates.py
coords_nsga2/visualization/pareto_front.py
coords_nsga2/visualization/solution_comparison.py
coords_nsga2/visualization/utils.py
coords_nsga2-2.7.0.dist-info/METADATA
coords_nsga2-2.7.0.dist-info/WHEEL
coords_nsga2-2.7.0.dist-info/licenses/LICENSE
coords_nsga2-2.7.0.dist-info/RECORD
