Metadata-Version: 2.4
Name: coords-nsga2
Version: 2.7.0
Summary: A Python library implementing a coordinate-based NSGA-II for multi-objective optimization.
Project-URL: Homepage, https://coords-nsga2.cc
Author-email: Xiaofeng Zhang <xiaofeng1001@outlook.com>
License-Expression: Apache-2.0
License-File: LICENSE
Keywords: coordinates,genetic-algorithm,nsga2,optimization
Classifier: Development Status :: 5 - Production/Stable
Classifier: Intended Audience :: Developers
Classifier: Intended Audience :: Education
Classifier: Intended Audience :: Science/Research
Classifier: License :: OSI Approved :: Apache Software License
Classifier: Operating System :: OS Independent
Classifier: Programming Language :: Python :: 3
Classifier: Programming Language :: Python :: 3.8
Classifier: Programming Language :: Python :: 3.9
Classifier: Programming Language :: Python :: 3.10
Classifier: Programming Language :: Python :: 3.11
Classifier: Programming Language :: Python :: 3.12
Classifier: Programming Language :: Python :: 3.13
Classifier: Topic :: Scientific/Engineering
Classifier: Topic :: Scientific/Engineering :: Mathematics
Requires-Python: >=3.8
Requires-Dist: joblib>=1.4
Requires-Dist: matplotlib>=3.6
Requires-Dist: numpy>=1.23
Requires-Dist: shapely>=2
Requires-Dist: tqdm>=4.64
Provides-Extra: docs
Requires-Dist: mkdocs; extra == 'docs'
Requires-Dist: mkdocs-material; extra == 'docs'
Requires-Dist: mkdocs-static-i18n; extra == 'docs'
Provides-Extra: test
Requires-Dist: coverage[toml]>=7.5; extra == 'test'
Requires-Dist: hypothesis>=6.100; extra == 'test'
Requires-Dist: pre-commit; extra == 'test'
Requires-Dist: pytest-cov>=5; extra == 'test'
Requires-Dist: pytest>=8.2; extra == 'test'
Requires-Dist: ruff>=0.11; extra == 'test'
Requires-Dist: scipy; extra == 'test'
